CHANGELOG.md
CONTRIBUTING.md
LICENSE.md
MANIFEST.in
README.md
pyproject.toml
setup.cfg
setup.py
pdf_importer/Importers.py
pdf_importer/__init__.py
pdf_importer/__main__.py
pdf_importer/__project__.py
pdf_importer/pdf_importer.py
pdf_importer.egg-info/PKG-INFO
pdf_importer.egg-info/SOURCES.txt
pdf_importer.egg-info/dependency_links.txt
pdf_importer.egg-info/requires.txt
pdf_importer.egg-info/top_level.txt