Metadata-Version: 2.1
Name: pdf-importer
Version: 0.3
Summary: A PDF importer to generate CSV files from bank statements
Home-page: https://github.com/c-vigo/StatementPDFImporter
Author: Carlos Vigo
Author-email: <carlosv@phys.ethz.ch>
License: GPLv3
Keywords: PDF
Platform: UNKNOWN
Classifier: Programming Language :: Python :: 3.6
Classifier: License :: OSI Approved :: GNU General Public License v3 (GPLv3)
Classifier: Operating System :: POSIX :: Linux
Requires-Python: >=3.6
